graph_comp/__init__.py
graph_comp/node.py
graph_comp/util.py
graph_comp-0.2.0.dist-info/METADATA
graph_comp-0.2.0.dist-info/WHEEL
graph_comp-0.2.0.dist-info/top_level.txt
graph_comp-0.2.0.dist-info/RECORD
