Metadata-Version: 2.1
Name: graph-comp
Version: 0.2.0
Summary: Simple computation graph library with cost support.
Author: Brian Guarraci
License: MIT
